proxsurv/__init__.py
proxsurv/utils.py
proxsurv/cbrsurv/__init__.py
proxsurv/cbrsurv/cobrasurvival.py
proxsurv/cbrsurv/distance_functions.py
proxsurv/cbrsurv/indexcalculator.py
proxsurv/cbrsurv/npsurvival_models.py
proxsurv-0.0.3.dist-info/LICENSE
proxsurv-0.0.3.dist-info/METADATA
proxsurv-0.0.3.dist-info/WHEEL
proxsurv-0.0.3.dist-info/top_level.txt
proxsurv-0.0.3.dist-info/RECORD
