Metadata-Version: 2.1
Name: proxsurv
Version: 0.0.3
Summary: Proximity Based Survival Analysis
Author-email: Rahul Goswami <yuvrajiro@gmail.com>
License: MIT License
Keywords: Proximity,Machine Learning,Survival Analysis,Ensemble Learning
Classifier: License :: OSI Approved :: MIT License
Classifier: Programming Language :: Python
Classifier: Programming Language :: Python :: 3
License-File: LICENSE
